{
  "aodamiao":{
    "type":"image",
    "container":[
      {
        "text":"aodamiao-1",
        "icon":"<img src='https://ouo.chlorinechan.top/aodamiao/01.webp'>"
      },
      {
        "text":"aodamiao-2",
        "icon":"<img src='https://ouo.chlorinechan.top/aodamiao/02.webp'>"
      },
      {
        "text":"aodamiao-3",
        "icon":"<img src='https://ouo.chlorinechan.top/aodamiao/03.webp'>"
      },
      {
        "text":"aodamiao-4",
        "icon":"<img src='https://ouo.chlorinechan.top/aodamiao/04.webp'>"
      },
      {
        "text":"aodamiao-5",
        "icon":"<img src='https://ouo.chlorinechan.top/aodamiao/05.webp'>"
      },
      {
        "text":"aodamiao-6",
        "icon":"<img src='https://ouo.chlorinechan.top/aodamiao/06.webp'>"
      },
      {
        "text":"aodamiao-7",
        "icon":"<img src='https://ouo.chlorinechan.top/aodamiao/07.webp'>"
      },
      {
        "text":"aodamiao-8",
        "icon":"<img src='https://ouo.chlorinechan.top/aodamiao/08.webp'>"
      },
      {
        "text":"aodamiao-9",
        "icon":"<img src='https://ouo.chlorinechan.top/aodamiao/09.webp'>"
      },
      {
        "text":"aodamiao-10",
        "icon":"<img src='https://ouo.chlorinechan.top/aodamiao/10.webp'>"
      },
      {
        "text":"aodamiao-11",
        "icon":"<img src='https://ouo.chlorinechan.top/aodamiao/11.webp'>"
      },
      {
        "text":"aodamiao-12",
        "icon":"<img src='https://ouo.chlorinechan.top/aodamiao/12.webp'>"
      },
      {
        "text":"aodamiao-13",
        "icon":"<img src='https://ouo.chlorinechan.top/aodamiao/13.webp'>"
      },
      {
        "text":"aodamiao-14",
        "icon":"<img src='https://ouo.chlorinechan.top/aodamiao/14.webp'>"
      },
      {
        "text":"aodamiao-15",
        "icon":"<img src='https://ouo.chlorinechan.top/aodamiao/15.webp'>"
      },
      {
        "text":"aodamiao-16",
        "icon":"<img src='https://ouo.chlorinechan.top/aodamiao/16.webp'>"
      },
      {
        "text":"aodamiao-17",
        "icon":"<img src='https://ouo.chlorinechan.top/aodamiao/17.webp'>"
      },
      {
        "text":"aodamiao-18",
        "icon":"<img src='https://ouo.chlorinechan.top/aodamiao/18.webp'>"
      },
      {
        "text":"aodamiao-19",
        "icon":"<img src='https://ouo.chlorinechan.top/aodamiao/19.webp'>"
      },
      {
        "text":"aodamiao-20",
        "icon":"<img src='https://ouo.chlorinechan.top/aodamiao/20.webp'>"
      },
      {
        "text":"aodamiao-21",
        "icon":"<img src='https://ouo.chlorinechan.top/aodamiao/21.webp'>"
      },
      {
        "text":"aodamiao-22",
        "icon":"<img src='https://ouo.chlorinechan.top/aodamiao/22.webp'>"
      },
      {
        "text":"aodamiao-23",
        "icon":"<img src='https://ouo.chlorinechan.top/aodamiao/23.webp'>"
      },
      {
        "text":"aodamiao-24",
        "icon":"<img src='https://ouo.chlorinechan.top/aodamiao/24.webp'>"
      },
      {
        "text":"aodamiao-25",
        "icon":"<img src='https://ouo.chlorinechan.top/aodamiao/25.webp'>"
      },
      {
        "text":"aodamiao-26",
        "icon":"<img src='https://ouo.chlorinechan.top/aodamiao/26.webp'>"
      },
      {
        "text":"aodamiao-27",
        "icon":"<img src='https://ouo.chlorinechan.top/aodamiao/27.webp'>"
      },
      {
        "text":"aodamiao-28",
        "icon":"<img src='https://ouo.chlorinechan.top/aodamiao/28.webp'>"
      },
      {
        "text":"aodamiao-29",
        "icon":"<img src='https://ouo.chlorinechan.top/aodamiao/29.webp'>"
      },
      {
        "text":"aodamiao-30",
        "icon":"<img src='https://ouo.chlorinechan.top/aodamiao/30.webp'>"
      },
      {
        "text":"aodamiao-31",
        "icon":"<img src='https://ouo.chlorinechan.top/aodamiao/31.webp'>"
      },
      {
        "text":"aodamiao-32",
        "icon":"<img src='https://ouo.chlorinechan.top/aodamiao/32.webp'>"
      },
      {
        "text":"aodamiao-33",
        "icon":"<img src='https://ouo.chlorinechan.top/aodamiao/33.webp'>"
      },
      {
        "text":"aodamiao-34",
        "icon":"<img src='https://ouo.chlorinechan.top/aodamiao/34.webp'>"
      },
      {
        "text":"aodamiao-35",
        "icon":"<img src='https://ouo.chlorinechan.top/aodamiao/35.webp'>"
      },
      {
        "text":"aodamiao-36",
        "icon":"<img src='https://ouo.chlorinechan.top/aodamiao/36.webp'>"
      },
      {
        "text":"aodamiao-37",
        "icon":"<img src='https://ouo.chlorinechan.top/aodamiao/37.webp'>"
      },
      {
        "text":"aodamiao-38",
        "icon":"<img src='https://ouo.chlorinechan.top/aodamiao/38.webp'>"
      },
      {
        "text":"aodamiao-39",
        "icon":"<img src='https://ouo.chlorinechan.top/aodamiao/39.webp'>"
      },
      {
        "text":"aodamiao-40",
        "icon":"<img src='https://ouo.chlorinechan.top/aodamiao/40.webp'>"
      }
    ]
  }
}